{
  "name": "acloudviewer",
  "display_name": "ACloudViewer",
  "version": "3.1.0",
  "description": "3D point cloud and mesh processing via ACloudViewer binary CLI and JSON-RPC",
  "requires": "ACloudViewer binary on PATH or ACV_BINARY env var",
  "homepage": "https://asher-1.github.io/ACloudViewer",
  "install_cmd": "pip install git+https://github.com/Asher-1/CLI-Anything.git#subdirectory=acloudviewer/agent-harness",
  "entry_point": "cli-anything-acloudviewer",
  "skill_md": "acloudviewer/agent-harness/cli_anything/acloudviewer/skills/SKILL.md",
  "category": "3d",
  "contributor": "Asher-1",
  "contributor_url": "https://github.com/Asher-1"
}
